tudais/__init__.py
tudais/__main__.py
tudais/notebooks/classification/Titanic/.include_in_submission
tudais/notebooks/classification/Titanic/Untergang der Titanic.ipynb
tudais/notebooks/classification/Titanic/.ipynb_checkpoints/Untergang der Titanic-checkpoint.ipynb
tudais/notebooks/classification/Titanic/Data/.include_in_submission
tudais/notebooks/classification/Titanic/Data/titanic.csv
tudais/notebooks/classification/Titanic/Data/titanic_test.csv
tudais/notebooks/classification/Titanic/Images/.include_in_submission
tudais/notebooks/classification/Titanic/Images/IMG-Titanic-Banner.gif
tudais/notebooks/classification/Titanic/Images/IMG-Titanic-Footer.jpg
tudais/notebooks/classification/Titanic/Images/IMG-White-Star-Line.jpg
tudais/notebooks/classification/Titanic/Images/IMG-alert.png
tudais/notebooks/classification/Titanic/Images/IMG-blush.png
tudais/notebooks/classification/Titanic/Images/IMG-broom.png
tudais/notebooks/classification/Titanic/Images/IMG-crying.png
tudais/notebooks/classification/Titanic/Images/IMG-csv-in.png
tudais/notebooks/classification/Titanic/Images/IMG-csv-out.png
tudais/notebooks/classification/Titanic/Images/IMG-csv.png
tudais/notebooks/classification/Titanic/Images/IMG-diagonal-arrow.png
tudais/notebooks/classification/Titanic/Images/IMG-diagram.png
tudais/notebooks/classification/Titanic/Images/IMG-gears.png
tudais/notebooks/classification/Titanic/Images/IMG-hourglass.png
tudais/notebooks/classification/Titanic/Images/IMG-left-arrow.png
tudais/notebooks/classification/Titanic/Images/IMG-magnifying-glass.png
tudais/notebooks/classification/Titanic/Images/IMG-report.png
tudais/notebooks/classification/Titanic/Images/IMG-right-arrow.png
tudais/notebooks/classification/Wine-Quality/Klassifikation von Wein.ipynb
tudais/notebooks/classification/Wine-Quality/.ipynb_checkpoints/Klassifikation von Wein-checkpoint.ipynb
tudais/notebooks/classification/Wine-Quality/Data/winequality-red.csv
tudais-0.3.dist-info/LICENSE
tudais-0.3.dist-info/METADATA
tudais-0.3.dist-info/WHEEL
tudais-0.3.dist-info/entry_points.txt
tudais-0.3.dist-info/top_level.txt
tudais-0.3.dist-info/RECORD
