Metadata-Version: 2.1
Name: tudais
Version: 0.3
Summary: Supplemental material for the lecture Angewandte Intelligente Signalverarbeitung at TU Dresden
Home-page: http://github.com/TUD-STKS/tud-ais-package
Author: Simon Stone, Christian Kleiner, Peter Steiner
Author-email: christian.kleiner@tu-dresden.de
License: MIT
License-File: LICENSE
Requires-Dist: jupyterlab
Requires-Dist: pandas
Requires-Dist: scikit-learn
Requires-Dist: tudthemes
Requires-Dist: seaborn
